odoo/addons/account_invoice_tax_note/README.rst
odoo/addons/account_invoice_tax_note/__init__.py
odoo/addons/account_invoice_tax_note/__manifest__.py
odoo/addons/account_invoice_tax_note/i18n/account_invoice_tax_note.pot
odoo/addons/account_invoice_tax_note/i18n/de.po
odoo/addons/account_invoice_tax_note/i18n/es_PA.po
odoo/addons/account_invoice_tax_note/i18n/fr.po
odoo/addons/account_invoice_tax_note/models/__init__.py
odoo/addons/account_invoice_tax_note/models/account_move.py
odoo/addons/account_invoice_tax_note/models/account_tax_group.py
odoo/addons/account_invoice_tax_note/readme/CONTRIBUTORS.rst
odoo/addons/account_invoice_tax_note/readme/DESCRIPTION.rst
odoo/addons/account_invoice_tax_note/readme/USAGE.rst
odoo/addons/account_invoice_tax_note/reports/report_invoice_document.xml
odoo/addons/account_invoice_tax_note/static/description/icon.png
odoo/addons/account_invoice_tax_note/static/description/index.html
odoo/addons/account_invoice_tax_note/tests/__init__.py
odoo/addons/account_invoice_tax_note/tests/test_account_invoice.py
odoo13_addon_account_invoice_tax_note-13.0.1.0.1.dev6.dist-info/METADATA
odoo13_addon_account_invoice_tax_note-13.0.1.0.1.dev6.dist-info/WHEEL
odoo13_addon_account_invoice_tax_note-13.0.1.0.1.dev6.dist-info/top_level.txt
odoo13_addon_account_invoice_tax_note-13.0.1.0.1.dev6.dist-info/RECORD
